hcube/__init__.py
hcube/settings.py
hcube/api/__init__.py
hcube/api/backend.py
hcube/api/exceptions.py
hcube/api/models/__init__.py
hcube/api/models/aggregation.py
hcube/api/models/cube.py
hcube/api/models/dimensions.py
hcube/api/models/filters.py
hcube/api/models/group_filters.py
hcube/api/models/injections.py
hcube/api/models/materialized_views.py
hcube/api/models/metrics.py
hcube/api/models/ordering.py
hcube/api/models/query.py
hcube/api/models/transforms.py
hcube/backends/__init__.py
hcube/backends/naive.py
hcube/backends/postgres.py
hcube/backends/clickhouse/__init__.py
hcube/backends/clickhouse/backend.py
hcube/backends/clickhouse/data_sources.py
hcube/backends/clickhouse/dictionaries.py
hcube/backends/clickhouse/indexes.py
hcube/backends/clickhouse/types.py
hcube/backends/clickhouse/utils.py
hcube-0.99.0.dist-info/licenses/LICENSE
hcube-0.99.0.dist-info/METADATA
hcube-0.99.0.dist-info/WHEEL
hcube-0.99.0.dist-info/top_level.txt
hcube-0.99.0.dist-info/RECORD
