Metadata-Version: 2.4
Name: hcube
Version: 0.99.0
Summary: HCube is a simple ORM for working with hyper-cube OLAP data stored in various backends.
Author-email: Beda Kosata <beda@bigdigdata.com>
License: WTFPL
Requires-Python: >=3.12
License-File: LICENSE
Requires-Dist: clickhouse-driver==0.2.9
Requires-Dist: python-decouple>=3.5
Requires-Dist: psycopg2-binary>=2.9.11
Requires-Dist: clickhouse-pool>=0.5.3
Dynamic: license-file
